{"walls":[{"x1":8,"z1":8,"x2":24,"z2":8},{"x1":24,"z1":8,"x2":24,"z2":20},{"x1":24,"z1":20,"x2":8,"z2":20},{"x1":8,"z1":20,"x2":8,"z2":8},{"x1":8,"z1":14,"x2":14,"z2":14},{"x1":14,"z1":8,"x2":14,"z2":20},{"x1":18,"z1":8,"x2":18,"z2":10},{"x1":18,"z1":10,"x2":19,"z2":11},{"x1":19,"z1":11,"x2":19,"z2":12},{"x1":14,"z1":12,"x2":19,"z2":12}],"furniture":[{"type":"door","furnitureId":"f-1","x":20,"z":20,"rotation":3.141592653589793,"doorOpen":false},{"type":"window","furnitureId":"f-4","x":9,"z":20,"rotation":3.141592653589793,"doorOpen":false},{"type":"balcony_door","furnitureId":"f-6","x":24,"z":18.5,"rotation":1.5707963267948966,"doorOpen":false},{"type":"door","furnitureId":"f-7","x":14,"z":13,"rotation":1.5707963267948966,"doorOpen":false},{"type":"desk_medium","furnitureId":"f-12","x":13.5,"z":11,"rotation":23.561944901923464},{"type":"door","furnitureId":"f-13","x":14,"z":16.5,"rotation":1.5707963267948966,"doorOpen":false},{"type":"bed_single","furnitureId":"f-14","x":9,"z":15,"rotation":1.5707963267948966},{"type":"wardrobe","furnitureId":"f-15","x":8.5,"z":16.5,"rotation":1.5707963267948966,"doorOpen":false},{"type":"desk_small","furnitureId":"f-16","x":11.5,"z":19.5,"rotation":3.141592653589793},{"type":"shelf_medium","furnitureId":"f-17","x":10.5,"z":19.5,"rotation":3.141592653589793},{"type":"door","furnitureId":"f-18","x":14,"z":8.5,"rotation":-1.5707963267948966,"doorOpen":false},{"type":"sofa","furnitureId":"f-34","x":17.5,"z":18.5,"rotation":4.71238898038469},{"type":"table","furnitureId":"f-35","x":16.5,"z":18.5,"rotation":1.5707963267948966},{"type":"tv","furnitureId":"f-36","x":14,"z":18.5,"rotation":1.5707963267948966,"tvStyle":"wall_inset"},{"type":"carpet","furnitureId":"f-37","x":17,"z":18.5,"rotation":0,"sizeW":4,"sizeD":3,"carpetShape":"oval","carpetPattern":"border","carpetColor":"#bc7238","carpetAccent":"#1dd4d7"},{"type":"lamp_medium","furnitureId":"f-38","x":18,"z":19.5,"rotation":0},{"type":"plant_large","furnitureId":"f-39","x":23.5,"z":19.5,"rotation":0},{"type":"shelf_large_cabinet","furnitureId":"f-41","x":23.5,"z":16.5,"rotation":4.71238898038469,"doorOpen":false},{"type":"lamp_wall","furnitureId":"f-42","x":14,"z":14.5,"rotation":1.5707963267948966},{"type":"window_large","furnitureId":"f-55","x":24,"z":14.5,"rotation":-1.5707963267948966,"doorOpen":false},{"type":"shelf_small","furnitureId":"f-72","x":8.5,"z":10.5,"rotation":1.5707963267948968},{"type":"shelf_small","furnitureId":"f-73","x":10.5,"z":8.5,"rotation":12.566370614359176},{"type":"bed_double","furnitureId":"f-8","x":10,"z":10,"rotation":0.7853981633974484},{"type":"window_large","furnitureId":"f-75","x":8,"z":10.5,"rotation":1.5707963267948966,"doorOpen":false},{"type":"plant_medium","furnitureId":"f-77","x":8.5,"z":8.5,"rotation":0},{"type":"chair","furnitureId":"f-79","x":13,"z":11,"rotation":1.5707963267948966},{"type":"wardrobe","furnitureId":"f-80","x":10.2,"z":13.5,"rotation":3.141592653589793,"furnitureGroupId":"grp-35","groupAnchorId":"f-82","groupOffsetX":-0.9749999999999996,"groupOffsetZ":0,"groupMode":"row","doorOpen":false},{"type":"shelf_medium_cabinet","furnitureId":"f-82","x":11.174999999999999,"z":13.5,"rotation":3.1415926535897927,"furnitureGroupId":"grp-35","groupAnchorId":"f-82","groupOffsetX":0,"groupOffsetZ":0,"groupMode":"row","doorOpen":false},{"type":"wardrobe","furnitureId":"f-11","x":9,"z":13.5,"rotation":3.1415926535897927,"furnitureGroupId":"grp-35","groupAnchorId":"f-82","groupOffsetX":-2.174999999999999,"groupOffsetZ":0,"groupMode":"row","doorOpen":false},{"type":"window","furnitureId":"f-83","x":13,"z":20,"rotation":3.141592653589793,"doorOpen":false},{"type":"chair","furnitureId":"f-85","x":11.5,"z":19,"rotation":0},{"type":"bookshelf","furnitureId":"f-89","x":13.5,"z":14.5,"rotation":5.497787143782138},{"type":"shelf_medium","furnitureId":"f-86","x":13.5,"z":18,"rotation":-1.5707963267948968,"furnitureGroupId":"grp-37","groupAnchorId":"f-86","groupOffsetX":0,"groupOffsetZ":0,"groupMode":"row"},{"type":"shelf_medium","furnitureId":"f-87","x":13.5,"z":18.75,"rotation":-1.5707963267948883,"furnitureGroupId":"grp-37","groupAnchorId":"f-86","groupOffsetX":0,"groupOffsetZ":0.75,"groupMode":"row"},{"type":"kitchen_fridge","furnitureId":"f-45","x":19.075,"z":8.500000000000007,"rotation":3.0628549591415595e-15,"furnitureGroupId":"grp-39","groupAnchorId":"f-45","groupOffsetX":0,"groupOffsetZ":0,"groupMode":"row","doorOpen":false},{"type":"kitchen_dishwasher","furnitureId":"f-49","x":19.7,"z":8.500000000000005,"rotation":3.0628549591415595e-15,"furnitureGroupId":"grp-39","groupAnchorId":"f-45","groupOffsetX":0.625,"groupOffsetZ":-1.7763568394002505e-15,"groupMode":"row","doorOpen":false},{"type":"kitchen_unit","furnitureId":"f-27","x":20.5,"z":8.500000000000004,"rotation":3.0628549591415595e-15,"furnitureGroupId":"grp-39","groupAnchorId":"f-45","groupOffsetX":1.4250000000000007,"groupOffsetZ":-3.552713678800501e-15,"groupMode":"row"},{"type":"kitchen_unit","furnitureId":"f-28","x":21.5,"z":8.5,"rotation":3.0628549591415595e-15,"furnitureGroupId":"grp-39","groupAnchorId":"f-45","groupOffsetX":2.4250000000000007,"groupOffsetZ":-7.105427357601002e-15,"groupMode":"row"},{"type":"kitchen_unit","furnitureId":"f-51","x":22.5,"z":8.499999999999996,"rotation":-2.4492935982947064e-16,"furnitureGroupId":"grp-39","groupAnchorId":"f-45","groupOffsetX":3.4250000000000007,"groupOffsetZ":-1.0658141036401503e-14,"groupMode":"row"},{"type":"kitchen_oven","furnitureId":"f-44","x":23.3,"z":8.499999999999995,"rotation":3.0628549591415595e-15,"furnitureGroupId":"grp-39","groupAnchorId":"f-45","groupOffsetX":4.225000000000001,"groupOffsetZ":-1.2434497875801753e-14,"groupMode":"row","doorOpen":false},{"type":"door","furnitureId":"f-91","x":16,"z":12,"rotation":0,"doorOpen":false},{"type":"bathtub","furnitureId":"f-96","x":18,"z":11,"rotation":5.497787143782138},{"type":"toilet","furnitureId":"f-98","x":14.5,"z":11.5,"rotation":8.63937979737193},{"type":"lamp_wall","furnitureId":"f-100","x":17,"z":8,"rotation":0},{"type":"lamp_wall","furnitureId":"f-101","x":15,"z":8,"rotation":0},{"type":"lamp_wall","furnitureId":"f-102","x":17,"z":12,"rotation":3.141592653589793},{"type":"bath_shelf","furnitureId":"f-106","x":17.5,"z":9.499999999999998,"rotation":4.71238898038469,"furnitureGroupId":"grp-41","groupAnchorId":"f-104","groupOffsetX":0,"groupOffsetZ":0.6849999999999987,"groupMode":"row","doorOpen":false},{"type":"sink","furnitureId":"f-104","x":17.5,"z":8.815,"rotation":4.7123889803847,"furnitureGroupId":"grp-41","groupAnchorId":"f-104","groupOffsetX":0,"groupOffsetZ":0,"groupMode":"row"},{"type":"lamp_ceiling","furnitureId":"f-112","x":12,"z":11,"rotation":0},{"type":"lamp_ceiling","furnitureId":"f-114","x":11.5,"z":17,"rotation":0},{"type":"lamp_ceiling","furnitureId":"f-117","x":21,"z":18,"rotation":0},{"type":"lamp_wall","furnitureId":"f-120","x":21,"z":8,"rotation":0},{"type":"lamp_pendant","furnitureId":"f-123","x":22,"z":13,"rotation":0},{"type":"bookshelf","furnitureId":"f-40","x":14.499999999999996,"z":14.7,"rotation":1.5707963267949014,"furnitureGroupId":"grp-17","groupAnchorId":"f-40","groupOffsetX":0,"groupOffsetZ":0,"groupMode":"layout"},{"type":"bookshelf","furnitureId":"f-43","x":14.5,"z":15.5,"rotation":1.5707963267948963,"furnitureGroupId":"grp-17","groupAnchorId":"f-40","groupOffsetX":3.552713678800501e-15,"groupOffsetZ":0.8000000000000007,"groupMode":"layout"},{"type":"chair","furnitureId":"f-57","x":23,"z":13.5,"rotation":-2.3561944901923453,"furnitureGroupId":"grp-24","groupAnchorId":"f-31","groupOffsetX":2,"groupOffsetZ":1,"groupMode":"layout"},{"type":"chair","furnitureId":"f-48","x":21,"z":13.5,"rotation":2.356194490192345,"furnitureGroupId":"grp-24","groupAnchorId":"f-31","groupOffsetX":0,"groupOffsetZ":1,"groupMode":"layout"},{"type":"chair","furnitureId":"f-47","x":21.5,"z":14,"rotation":2.356194490192345,"furnitureGroupId":"grp-24","groupAnchorId":"f-31","groupOffsetX":0.5,"groupOffsetZ":1.5,"groupMode":"layout"},{"type":"chair","furnitureId":"f-56","x":22.5,"z":14,"rotation":-2.3561944901923453,"furnitureGroupId":"grp-24","groupAnchorId":"f-31","groupOffsetX":1.5,"groupOffsetZ":1.5,"groupMode":"layout"},{"type":"dining_table_xl","furnitureId":"f-53","x":22,"z":13,"rotation":-2.3561944901923453,"furnitureGroupId":"grp-24","groupAnchorId":"f-31","groupOffsetX":1,"groupOffsetZ":0.5,"groupMode":"layout"},{"type":"chair","furnitureId":"f-31","x":21,"z":12.5,"rotation":0.7853981633974484,"furnitureGroupId":"grp-24","groupAnchorId":"f-31","groupOffsetX":0,"groupOffsetZ":0,"groupMode":"layout"},{"type":"chair","furnitureId":"f-32","x":21.5,"z":12,"rotation":0.7853981633974484,"furnitureGroupId":"grp-24","groupAnchorId":"f-31","groupOffsetX":0.5,"groupOffsetZ":-0.5,"groupMode":"layout"},{"type":"chair","furnitureId":"f-30","x":22.5,"z":12,"rotation":-0.7853981633974485,"furnitureGroupId":"grp-24","groupAnchorId":"f-31","groupOffsetX":1.5,"groupOffsetZ":-0.5,"groupMode":"layout"},{"type":"chair","furnitureId":"f-33","x":23,"z":12.5,"rotation":-0.7853981633974485,"furnitureGroupId":"grp-24","groupAnchorId":"f-31","groupOffsetX":2,"groupOffsetZ":0,"groupMode":"layout"}],"wallColors":{}}